Metadata-Version: 2.1
Name: NudeNetClassifier
Version: 2.1
Summary: A Neural Net for Nudity Detection. Classifier only.
Home-page: https://github.com/platelminto/NudeNetClassifier
Author: Giorgio Momigliano
Author-email: gmomigliano@protonmail.com
License: GPLv3
Classifier: License :: OSI Approved :: GNU General Public License v3 (GPLv3)
Classifier: Programming Language :: Python
Classifier: Programming Language :: Python :: 3
Classifier: Programming Language :: Python :: 3.6
Classifier: Programming Language :: Python :: Implementation :: CPython
Classifier: Programming Language :: Python :: Implementation :: PyPy
Requires-Python: >=3.6.0
License-File: LICENSE.md
